calysto_bash/__init__.py
calysto_bash/__main__.py
calysto_bash/kernel.json
calysto_bash/kernel.py
calysto_bash/images/logo-32x32.png
calysto_bash/images/logo-64x64.png
calysto_bash-0.2.2.data/data/share/jupyter/kernels/calysto_bash/kernel.json
calysto_bash-0.2.2.data/data/share/jupyter/kernels/calysto_bash/logo-32x32.png
calysto_bash-0.2.2.data/data/share/jupyter/kernels/calysto_bash/logo-64x64.png
calysto_bash-0.2.2.dist-info/LICENSE
calysto_bash-0.2.2.dist-info/METADATA
calysto_bash-0.2.2.dist-info/WHEEL
calysto_bash-0.2.2.dist-info/top_level.txt
calysto_bash-0.2.2.dist-info/RECORD
