Metadata-Version: 2.1
Name: calysto-bash
Version: 0.2.2
Summary: A Jupyter kernel for Bash.
Home-page: http://github.com/Calysto/calysto_bash
Maintainer: Steven Silvester
Maintainer-email: steven.silvester@ieee.org
License: BSD
Download-URL: http://github.com/Calysto/calysto_bash
Platform: Any
Classifier: Intended Audience :: Science/Research
Classifier: License :: OSI Approved :: BSD License
Classifier: Operating System :: OS Independent
Classifier: Programming Language :: Python
Classifier: Programming Language :: Python :: 2.7
Classifier: Programming Language :: Python :: 3.3
Classifier: Programming Language :: Python :: 3.4
Classifier: Topic :: Scientific/Engineering
Classifier: Topic :: Software Development
Classifier: Topic :: System :: Shells
Requires: metakernel (>=0.20.7)
Requires: jupyter_client (>=4.3.0)
Requires: ipykernel
Requires-Dist: metakernel (>=0.20.7)
Requires-Dist: jupyter-client (>=4.3.0)
Requires-Dist: ipykernel
